{
   "results" : [
      {
         "elevation" : 0,
         "location" : {
            "lat" : 50.67793,
            "lng" : -3.13997
         },
         "resolution" : 152.7032318115234
      },
      {
         "elevation" : 0,
         "location" : {
            "lat" : 50.67813,
            "lng" : -3.13997
         },
         "resolution" : 152.7032318115234
      },
      {
         "elevation" : 0,
         "location" : {
            "lat" : 50.67833,
            "lng" : -3.13997
         },
         "resolution" : 152.7032318115234
      },
      {
         "elevation" : 0,
         "location" : {
            "lat" : 50.67852,
            "lng" : -3.13997
         },
         "resolution" : 152.7032318115234
      },
      {
         "elevation" : 0,
         "location" : {
            "lat" : 50.67872,
            "lng" : -3.13997
         },
         "resolution" : 152.7032318115234
      },
      {
         "elevation" : 0,
         "location" : {
            "lat" : 50.67891,
            "lng" : -3.13997
         },
         "resolution" : 152.7032318115234
      },
      {
         "elevation" : 0,
         "location" : {
            "lat" : 50.67911,
            "lng" : -3.13997
         },
         "resolution" : 152.7032318115234
      },
      {
         "elevation" : 0,
         "location" : {
            "lat" : 50.67931,
            "lng" : -3.13997
         },
         "resolution" : 152.7032318115234
      },
      {
         "elevation" : 0,
         "location" : {
            "lat" : 50.6795,
            "lng" : -3.13997
         },
         "resolution" : 152.7032318115234
      },
      {
         "elevation" : 0,
         "location" : {
            "lat" : 50.6797,
            "lng" : -3.13997
         },
         "resolution" : 152.7032318115234
      },
      {
         "elevation" : 0,
         "location" : {
            "lat" : 50.6799,
            "lng" : -3.13997
         },
         "resolution" : 152.7032318115234
      },
      {
         "elevation" : 0,
         "location" : {
            "lat" : 50.68009,
            "lng" : -3.13997
         },
         "resolution" : 152.7032318115234
      },
      {
         "elevation" : 0,
         "location" : {
            "lat" : 50.68029,
            "lng" : -3.13997
         },
         "resolution" : 152.7032318115234
      },
      {
         "elevation" : 0,
         "location" : {
            "lat" : 50.68048,
            "lng" : -3.13997
         },
         "resolution" : 152.7032318115234
      },
      {
         "elevation" : 0,
         "location" : {
            "lat" : 50.68068,
            "lng" : -3.13997
         },
         "resolution" : 152.7032318115234
      },
      {
         "elevation" : 0,
         "location" : {
            "lat" : 50.68088,
            "lng" : -3.13997
         },
         "resolution" : 152.7032318115234
      },
      {
         "elevation" : 0,
         "location" : {
            "lat" : 50.68108,
            "lng" : -3.13997
         },
         "resolution" : 152.7032318115234
      },
      {
         "elevation" : 0,
         "location" : {
            "lat" : 50.68127,
            "lng" : -3.13997
         },
         "resolution" : 152.7032318115234
      },
      {
         "elevation" : 0,
         "location" : {
            "lat" : 50.68147,
            "lng" : -3.13997
         },
         "resolution" : 152.7032318115234
      },
      {
         "elevation" : 0,
         "location" : {
            "lat" : 50.68166,
            "lng" : -3.13997
         },
         "resolution" : 152.7032318115234
      },
      {
         "elevation" : 0,
         "location" : {
            "lat" : 50.68186,
            "lng" : -3.13997
         },
         "resolution" : 152.7032318115234
      },
      {
         "elevation" : 0,
         "location" : {
            "lat" : 50.68206,
            "lng" : -3.13997
         },
         "resolution" : 152.7032318115234
      },
      {
         "elevation" : 0,
         "location" : {
            "lat" : 50.68225,
            "lng" : -3.13997
         },
         "resolution" : 152.7032318115234
      },
      {
         "elevation" : 0,
         "location" : {
            "lat" : 50.68245,
            "lng" : -3.13997
         },
         "resolution" : 152.7032318115234
      },
      {
         "elevation" : 0,
         "location" : {
            "lat" : 50.68265,
            "lng" : -3.13997
         },
         "resolution" : 152.7032318115234
      },
      {
         "elevation" : 0,
         "location" : {
            "lat" : 50.68284,
            "lng" : -3.13997
         },
         "resolution" : 152.7032318115234
      },
      {
         "elevation" : 0,
         "location" : {
            "lat" : 50.68304,
            "lng" : -3.13997
         },
         "resolution" : 152.7032318115234
      },
      {
         "elevation" : 0,
         "location" : {
            "lat" : 50.68324,
            "lng" : -3.13997
         },
         "resolution" : 152.7032318115234
      },
      {
         "elevation" : 0,
         "location" : {
            "lat" : 50.68343,
            "lng" : -3.13997
         },
         "resolution" : 152.7032318115234
      },
      {
         "elevation" : 0,
         "location" : {
            "lat" : 50.68363,
            "lng" : -3.13997
         },
         "resolution" : 152.7032318115234
      },
      {
         "elevation" : 0,
         "location" : {
            "lat" : 50.68383,
            "lng" : -3.13997
         },
         "resolution" : 152.7032318115234
      },
      {
         "elevation" : 0,
         "location" : {
            "lat" : 50.68402,
            "lng" : -3.13997
         },
         "resolution" : 152.7032318115234
      },
      {
         "elevation" : 0,
         "location" : {
            "lat" : 50.68422,
            "lng" : -3.13997
         },
         "resolution" : 152.7032318115234
      },
      {
         "elevation" : 0,
         "location" : {
            "lat" : 50.68441,
            "lng" : -3.13997
         },
         "resolution" : 152.7032318115234
      },
      {
         "elevation" : 0,
         "location" : {
            "lat" : 50.68461,
            "lng" : -3.13997
         },
         "resolution" : 152.7032318115234
      },
      {
         "elevation" : 0,
         "location" : {
            "lat" : 50.68481,
            "lng" : -3.13997
         },
         "resolution" : 152.7032318115234
      },
      {
         "elevation" : 0,
         "location" : {
            "lat" : 50.68501,
            "lng" : -3.13997
         },
         "resolution" : 152.7032318115234
      },
      {
         "elevation" : 0,
         "location" : {
            "lat" : 50.6852,
            "lng" : -3.13997
         },
         "resolution" : 152.7032318115234
      },
      {
         "elevation" : 0,
         "location" : {
            "lat" : 50.6854,
            "lng" : -3.13997
         },
         "resolution" : 152.7032318115234
      },
      {
         "elevation" : 0,
         "location" : {
            "lat" : 50.68559,
            "lng" : -3.13997
         },
         "resolution" : 152.7032318115234
      },
      {
         "elevation" : 0,
         "location" : {
            "lat" : 50.68579,
            "lng" : -3.13997
         },
         "resolution" : 152.7032318115234
      },
      {
         "elevation" : 0.002136197872459888,
         "location" : {
            "lat" : 50.68599,
            "lng" : -3.13997
         },
         "resolution" : 152.7032318115234
      },
      {
         "elevation" : 0.7645947933197021,
         "location" : {
            "lat" : 50.68618,
            "lng" : -3.13997
         },
         "resolution" : 152.7032318115234
      },
      {
         "elevation" : 2.891299486160278,
         "location" : {
            "lat" : 50.68638,
            "lng" : -3.13997
         },
         "resolution" : 152.7032318115234
      },
      {
         "elevation" : 20.28654098510742,
         "location" : {
            "lat" : 50.68658,
            "lng" : -3.13997
         },
         "resolution" : 152.7032318115234
      },
      {
         "elevation" : 46.54947280883789,
         "location" : {
            "lat" : 50.68677,
            "lng" : -3.13997
         },
         "resolution" : 152.7032318115234
      },
      {
         "elevation" : 66.78145599365234,
         "location" : {
            "lat" : 50.68697,
            "lng" : -3.13997
         },
         "resolution" : 152.7032318115234
      },
      {
         "elevation" : 80.42688751220703,
         "location" : {
            "lat" : 50.68716,
            "lng" : -3.13997
         },
         "resolution" : 152.7032318115234
      },
      {
         "elevation" : 93.92374420166016,
         "location" : {
            "lat" : 50.68736,
            "lng" : -3.13997
         },
         "resolution" : 152.7032318115234
      },
      {
         "elevation" : 109.542106628418,
         "location" : {
            "lat" : 50.68756,
            "lng" : -3.13997
         },
         "resolution" : 152.7032318115234
      },
      {
         "elevation" : 112.6283493041992,
         "location" : {
            "lat" : 50.68776,
            "lng" : -3.13997
         },
         "resolution" : 152.7032318115234
      },
      {
         "elevation" : 109.4794082641602,
         "location" : {
            "lat" : 50.68795,
            "lng" : -3.13997
         },
         "resolution" : 152.7032318115234
      },
      {
         "elevation" : 105.0513610839844,
         "location" : {
            "lat" : 50.68815,
            "lng" : -3.13997
         },
         "resolution" : 152.7032318115234
      },
      {
         "elevation" : 101.3101654052734,
         "location" : {
            "lat" : 50.68834,
            "lng" : -3.13997
         },
         "resolution" : 152.7032318115234
      },
      {
         "elevation" : 95.28562927246094,
         "location" : {
            "lat" : 50.68854,
            "lng" : -3.13997
         },
         "resolution" : 152.7032318115234
      },
      {
         "elevation" : 86.80438995361328,
         "location" : {
            "lat" : 50.68874,
            "lng" : -3.13997
         },
         "resolution" : 152.7032318115234
      },
      {
         "elevation" : 81.63949584960938,
         "location" : {
            "lat" : 50.68893,
            "lng" : -3.13997
         },
         "resolution" : 152.7032318115234
      },
      {
         "elevation" : 71.03738403320312,
         "location" : {
            "lat" : 50.68913,
            "lng" : -3.13997
         },
         "resolution" : 152.7032318115234
      },
      {
         "elevation" : 53.93427276611328,
         "location" : {
            "lat" : 50.68933,
            "lng" : -3.13997
         },
         "resolution" : 152.7032318115234
      },
      {
         "elevation" : 46.02141189575195,
         "location" : {
            "lat" : 50.68952,
            "lng" : -3.13997
         },
         "resolution" : 152.7032318115234
      },
      {
         "elevation" : 39.90383148193359,
         "location" : {
            "lat" : 50.68972,
            "lng" : -3.13997
         },
         "resolution" : 152.7032318115234
      },
      {
         "elevation" : 40.51510238647461,
         "location" : {
            "lat" : 50.68991,
            "lng" : -3.13997
         },
         "resolution" : 152.7032318115234
      },
      {
         "elevation" : 43.0897331237793,
         "location" : {
            "lat" : 50.69011,
            "lng" : -3.13997
         },
         "resolution" : 152.7032318115234
      },
      {
         "elevation" : 44.48502731323242,
         "location" : {
            "lat" : 50.69031,
            "lng" : -3.13997
         },
         "resolution" : 152.7032318115234
      },
      {
         "elevation" : 48.63178634643555,
         "location" : {
            "lat" : 50.69051,
            "lng" : -3.13997
         },
         "resolution" : 152.7032318115234
      },
      {
         "elevation" : 53.52742767333984,
         "location" : {
            "lat" : 50.6907,
            "lng" : -3.13997
         },
         "resolution" : 152.7032318115234
      },
      {
         "elevation" : 59.01296234130859,
         "location" : {
            "lat" : 50.6909,
            "lng" : -3.13997
         },
         "resolution" : 152.7032318115234
      },
      {
         "elevation" : 63.06522750854492,
         "location" : {
            "lat" : 50.69109,
            "lng" : -3.13997
         },
         "resolution" : 152.7032318115234
      },
      {
         "elevation" : 69.07063293457031,
         "location" : {
            "lat" : 50.69129,
            "lng" : -3.13997
         },
         "resolution" : 152.7032318115234
      },
      {
         "elevation" : 74.57390594482422,
         "location" : {
            "lat" : 50.69149,
            "lng" : -3.13997
         },
         "resolution" : 152.7032318115234
      },
      {
         "elevation" : 75.81086730957031,
         "location" : {
            "lat" : 50.69168,
            "lng" : -3.13997
         },
         "resolution" : 152.7032318115234
      },
      {
         "elevation" : 74.98150634765625,
         "location" : {
            "lat" : 50.69188,
            "lng" : -3.13997
         },
         "resolution" : 152.7032318115234
      },
      {
         "elevation" : 73.80593109130859,
         "location" : {
            "lat" : 50.69208,
            "lng" : -3.13997
         },
         "resolution" : 152.7032318115234
      },
      {
         "elevation" : 69.75326538085938,
         "location" : {
            "lat" : 50.69227,
            "lng" : -3.13997
         },
         "resolution" : 152.7032318115234
      },
      {
         "elevation" : 65.41085052490234,
         "location" : {
            "lat" : 50.69247,
            "lng" : -3.13997
         },
         "resolution" : 152.7032318115234
      },
      {
         "elevation" : 58.49476623535156,
         "location" : {
            "lat" : 50.69267,
            "lng" : -3.13997
         },
         "resolution" : 152.7032318115234
      },
      {
         "elevation" : 53.44011306762695,
         "location" : {
            "lat" : 50.69286,
            "lng" : -3.13997
         },
         "resolution" : 152.7032318115234
      },
      {
         "elevation" : 48.93043518066406,
         "location" : {
            "lat" : 50.69306,
            "lng" : -3.13997
         },
         "resolution" : 152.7032318115234
      },
      {
         "elevation" : 43.74154663085938,
         "location" : {
            "lat" : 50.69326,
            "lng" : -3.13997
         },
         "resolution" : 152.7032318115234
      },
      {
         "elevation" : 38.93559265136719,
         "location" : {
            "lat" : 50.69345,
            "lng" : -3.13997
         },
         "resolution" : 152.7032318115234
      },
      {
         "elevation" : 39.34283447265625,
         "location" : {
            "lat" : 50.69365,
            "lng" : -3.13997
         },
         "resolution" : 152.7032318115234
      },
      {
         "elevation" : 36.70328521728516,
         "location" : {
            "lat" : 50.69384,
            "lng" : -3.13997
         },
         "resolution" : 152.7032318115234
      },
      {
         "elevation" : 36.23311996459961,
         "location" : {
            "lat" : 50.69404,
            "lng" : -3.13997
         },
         "resolution" : 152.7032318115234
      },
      {
         "elevation" : 38.60050582885742,
         "location" : {
            "lat" : 50.69424,
            "lng" : -3.13997
         },
         "resolution" : 152.7032318115234
      },
      {
         "elevation" : 40.53908920288086,
         "location" : {
            "lat" : 50.69444,
            "lng" : -3.13997
         },
         "resolution" : 152.7032318115234
      },
      {
         "elevation" : 41.28998947143555,
         "location" : {
            "lat" : 50.69463,
            "lng" : -3.13997
         },
         "resolution" : 152.7032318115234
      },
      {
         "elevation" : 41.99404907226562,
         "location" : {
            "lat" : 50.69483,
            "lng" : -3.13997
         },
         "resolution" : 152.7032318115234
      },
      {
         "elevation" : 43.6009521484375,
         "location" : {
            "lat" : 50.69502,
            "lng" : -3.13997
         },
         "resolution" : 152.7032318115234
      },
      {
         "elevation" : 48.75854873657227,
         "location" : {
            "lat" : 50.69522,
            "lng" : -3.13997
         },
         "resolution" : 152.7032318115234
      },
      {
         "elevation" : 52.42127990722656,
         "location" : {
            "lat" : 50.69542,
            "lng" : -3.13997
         },
         "resolution" : 152.7032318115234
      },
      {
         "elevation" : 55.53617095947266,
         "location" : {
            "lat" : 50.69561,
            "lng" : -3.13997
         },
         "resolution" : 152.7032318115234
      },
      {
         "elevation" : 60.58596420288086,
         "location" : {
            "lat" : 50.69581,
            "lng" : -3.13997
         },
         "resolution" : 152.7032318115234
      },
      {
         "elevation" : 67.16570281982422,
         "location" : {
            "lat" : 50.69601,
            "lng" : -3.13997
         },
         "resolution" : 152.7032318115234
      },
      {
         "elevation" : 70.29200744628906,
         "location" : {
            "lat" : 50.6962,
            "lng" : -3.13997
         },
         "resolution" : 152.7032318115234
      },
      {
         "elevation" : 74.42095947265625,
         "location" : {
            "lat" : 50.6964,
            "lng" : -3.13997
         },
         "resolution" : 152.7032318115234
      },
      {
         "elevation" : 77.81533050537109,
         "location" : {
            "lat" : 50.69659,
            "lng" : -3.13997
         },
         "resolution" : 152.7032318115234
      },
      {
         "elevation" : 82.93068695068359,
         "location" : {
            "lat" : 50.69679,
            "lng" : -3.13997
         },
         "resolution" : 152.7032318115234
      },
      {
         "elevation" : 88.072998046875,
         "location" : {
            "lat" : 50.69699,
            "lng" : -3.13997
         },
         "resolution" : 152.7032318115234
      },
      {
         "elevation" : 91.57752990722656,
         "location" : {
            "lat" : 50.69719,
            "lng" : -3.13997
         },
         "resolution" : 152.7032318115234
      },
      {
         "elevation" : 93.71228790283203,
         "location" : {
            "lat" : 50.69738,
            "lng" : -3.13997
         },
         "resolution" : 152.7032318115234
      },
      {
         "elevation" : 97.82758331298828,
         "location" : {
            "lat" : 50.69758,
            "lng" : -3.13997
         },
         "resolution" : 152.7032318115234
      },
      {
         "elevation" : 104.0042572021484,
         "location" : {
            "lat" : 50.69777,
            "lng" : -3.13997
         },
         "resolution" : 152.7032318115234
      },
      {
         "elevation" : 108.4864654541016,
         "location" : {
            "lat" : 50.69797,
            "lng" : -3.13997
         },
         "resolution" : 152.7032318115234
      },
      {
         "elevation" : 111.7683334350586,
         "location" : {
            "lat" : 50.69817,
            "lng" : -3.13997
         },
         "resolution" : 152.7032318115234
      },
      {
         "elevation" : 114.1654052734375,
         "location" : {
            "lat" : 50.69836,
            "lng" : -3.13997
         },
         "resolution" : 152.7032318115234
      },
      {
         "elevation" : 117.0054321289062,
         "location" : {
            "lat" : 50.69856,
            "lng" : -3.13997
         },
         "resolution" : 152.7032318115234
      },
      {
         "elevation" : 120.6688842773438,
         "location" : {
            "lat" : 50.69876,
            "lng" : -3.13997
         },
         "resolution" : 152.7032318115234
      },
      {
         "elevation" : 124.0870590209961,
         "location" : {
            "lat" : 50.69895,
            "lng" : -3.13997
         },
         "resolution" : 152.7032318115234
      },
      {
         "elevation" : 128.1269073486328,
         "location" : {
            "lat" : 50.69915,
            "lng" : -3.13997
         },
         "resolution" : 152.7032318115234
      },
      {
         "elevation" : 129.9009857177734,
         "location" : {
            "lat" : 50.69934,
            "lng" : -3.13997
         },
         "resolution" : 152.7032318115234
      },
      {
         "elevation" : 131.5961151123047,
         "location" : {
            "lat" : 50.69954,
            "lng" : -3.13997
         },
         "resolution" : 152.7032318115234
      },
      {
         "elevation" : 133.7102355957031,
         "location" : {
            "lat" : 50.69974,
            "lng" : -3.13997
         },
         "resolution" : 152.7032318115234
      },
      {
         "elevation" : 137.1502227783203,
         "location" : {
            "lat" : 50.69994,
            "lng" : -3.13997
         },
         "resolution" : 152.7032318115234
      },
      {
         "elevation" : 139.70263671875,
         "location" : {
            "lat" : 50.70013,
            "lng" : -3.13997
         },
         "resolution" : 152.7032318115234
      },
      {
         "elevation" : 142.7337188720703,
         "location" : {
            "lat" : 50.70033,
            "lng" : -3.13997
         },
         "resolution" : 152.7032318115234
      },
      {
         "elevation" : 145.7536468505859,
         "location" : {
            "lat" : 50.70052,
            "lng" : -3.13997
         },
         "resolution" : 152.7032318115234
      },
      {
         "elevation" : 148.5041961669922,
         "location" : {
            "lat" : 50.70072,
            "lng" : -3.13997
         },
         "resolution" : 152.7032318115234
      },
      {
         "elevation" : 150.8235931396484,
         "location" : {
            "lat" : 50.70092,
            "lng" : -3.13997
         },
         "resolution" : 152.7032318115234
      },
      {
         "elevation" : 151.3335266113281,
         "location" : {
            "lat" : 50.70111,
            "lng" : -3.13997
         },
         "resolution" : 152.7032318115234
      },
      {
         "elevation" : 151.4981231689453,
         "location" : {
            "lat" : 50.70131,
            "lng" : -3.13997
         },
         "resolution" : 152.7032318115234
      },
      {
         "elevation" : 152.2257690429688,
         "location" : {
            "lat" : 50.70151,
            "lng" : -3.13997
         },
         "resolution" : 152.7032318115234
      },
      {
         "elevation" : 151.9976654052734,
         "location" : {
            "lat" : 50.7017,
            "lng" : -3.13997
         },
         "resolution" : 152.7032318115234
      },
      {
         "elevation" : 151.5964965820312,
         "location" : {
            "lat" : 50.7019,
            "lng" : -3.13997
         },
         "resolution" : 152.7032318115234
      },
      {
         "elevation" : 151.2799072265625,
         "location" : {
            "lat" : 50.7021,
            "lng" : -3.13997
         },
         "resolution" : 152.7032318115234
      },
      {
         "elevation" : 150.7521667480469,
         "location" : {
            "lat" : 50.70229,
            "lng" : -3.13997
         },
         "resolution" : 152.7032318115234
      },
      {
         "elevation" : 150.4064483642578,
         "location" : {
            "lat" : 50.70249,
            "lng" : -3.13997
         },
         "resolution" : 152.7032318115234
      },
      {
         "elevation" : 149.994140625,
         "location" : {
            "lat" : 50.70269,
            "lng" : -3.13997
         },
         "resolution" : 152.7032318115234
      },
      {
         "elevation" : 149.2362365722656,
         "location" : {
            "lat" : 50.70288,
            "lng" : -3.13997
         },
         "resolution" : 152.7032318115234
      },
      {
         "elevation" : 148.4446563720703,
         "location" : {
            "lat" : 50.70308,
            "lng" : -3.13997
         },
         "resolution" : 152.7032318115234
      },
      {
         "elevation" : 147.6408843994141,
         "location" : {
            "lat" : 50.70327,
            "lng" : -3.13997
         },
         "resolution" : 152.7032318115234
      },
      {
         "elevation" : 147.1621246337891,
         "location" : {
            "lat" : 50.70347,
            "lng" : -3.13997
         },
         "resolution" : 152.7032318115234
      },
      {
         "elevation" : 147.0019989013672,
         "location" : {
            "lat" : 50.70367,
            "lng" : -3.13997
         },
         "resolution" : 152.7032318115234
      },
      {
         "elevation" : 147.8908081054688,
         "location" : {
            "lat" : 50.70387,
            "lng" : -3.13997
         },
         "resolution" : 152.7032318115234
      },
      {
         "elevation" : 147.8394165039062,
         "location" : {
            "lat" : 50.70406,
            "lng" : -3.13997
         },
         "resolution" : 152.7032318115234
      },
      {
         "elevation" : 147.3734130859375,
         "location" : {
            "lat" : 50.70426,
            "lng" : -3.13997
         },
         "resolution" : 152.7032318115234
      },
      {
         "elevation" : 147.8168792724609,
         "location" : {
            "lat" : 50.70445,
            "lng" : -3.13997
         },
         "resolution" : 152.7032318115234
      },
      {
         "elevation" : 147.9134826660156,
         "location" : {
            "lat" : 50.70465,
            "lng" : -3.13997
         },
         "resolution" : 152.7032318115234
      },
      {
         "elevation" : 147.4922180175781,
         "location" : {
            "lat" : 50.70485,
            "lng" : -3.13997
         },
         "resolution" : 152.7032318115234
      },
      {
         "elevation" : 147.1360015869141,
         "location" : {
            "lat" : 50.70504,
            "lng" : -3.13997
         },
         "resolution" : 152.7032318115234
      },
      {
         "elevation" : 147.4608001708984,
         "location" : {
            "lat" : 50.70524,
            "lng" : -3.13997
         },
         "resolution" : 152.7032318115234
      },
      {
         "elevation" : 147.3495178222656,
         "location" : {
            "lat" : 50.70544,
            "lng" : -3.13997
         },
         "resolution" : 152.7032318115234
      },
      {
         "elevation" : 147.040283203125,
         "location" : {
            "lat" : 50.70563,
            "lng" : -3.13997
         },
         "resolution" : 152.7032318115234
      },
      {
         "elevation" : 146.7870788574219,
         "location" : {
            "lat" : 50.70583,
            "lng" : -3.13997
         },
         "resolution" : 152.7032318115234
      },
      {
         "elevation" : 146.2751312255859,
         "location" : {
            "lat" : 50.70602,
            "lng" : -3.13997
         },
         "resolution" : 152.7032318115234
      },
      {
         "elevation" : 145.6401062011719,
         "location" : {
            "lat" : 50.70622,
            "lng" : -3.13997
         },
         "resolution" : 152.7032318115234
      },
      {
         "elevation" : 145.42578125,
         "location" : {
            "lat" : 50.70642,
            "lng" : -3.13997
         },
         "resolution" : 152.7032318115234
      },
      {
         "elevation" : 145.3314514160156,
         "location" : {
            "lat" : 50.70662,
            "lng" : -3.13997
         },
         "resolution" : 152.7032318115234
      },
      {
         "elevation" : 145.3747863769531,
         "location" : {
            "lat" : 50.70681,
            "lng" : -3.13997
         },
         "resolution" : 152.7032318115234
      },
      {
         "elevation" : 144.6889038085938,
         "location" : {
            "lat" : 50.70701,
            "lng" : -3.13997
         },
         "resolution" : 152.7032318115234
      },
      {
         "elevation" : 145.0941467285156,
         "location" : {
            "lat" : 50.7072,
            "lng" : -3.13997
         },
         "resolution" : 152.7032318115234
      }
   ],
   "status" : "OK"
}
