{
   "results" : [
      {
         "elevation" : 88.30906677246094,
         "location" : {
            "lat" : 43.12248,
            "lng" : 17.73767
         },
         "resolution" : 152.7032318115234
      },
      {
         "elevation" : 88.58577728271484,
         "location" : {
            "lat" : 43.12267,
            "lng" : 17.73767
         },
         "resolution" : 152.7032318115234
      },
      {
         "elevation" : 88.645751953125,
         "location" : {
            "lat" : 43.12285,
            "lng" : 17.73767
         },
         "resolution" : 152.7032318115234
      },
      {
         "elevation" : 88.645751953125,
         "location" : {
            "lat" : 43.12304,
            "lng" : 17.73767
         },
         "resolution" : 152.7032318115234
      },
      {
         "elevation" : 88.645751953125,
         "location" : {
            "lat" : 43.12322,
            "lng" : 17.73767
         },
         "resolution" : 152.7032318115234
      },
      {
         "elevation" : 88.60512542724609,
         "location" : {
            "lat" : 43.12341,
            "lng" : 17.73767
         },
         "resolution" : 152.7032318115234
      },
      {
         "elevation" : 87.97105407714844,
         "location" : {
            "lat" : 43.1236,
            "lng" : 17.73767
         },
         "resolution" : 152.7032318115234
      },
      {
         "elevation" : 87.37034606933594,
         "location" : {
            "lat" : 43.12378,
            "lng" : 17.73767
         },
         "resolution" : 152.7032318115234
      },
      {
         "elevation" : 86.73626708984375,
         "location" : {
            "lat" : 43.12397,
            "lng" : 17.73767
         },
         "resolution" : 152.7032318115234
      },
      {
         "elevation" : 86.60673522949219,
         "location" : {
            "lat" : 43.12415,
            "lng" : 17.73767
         },
         "resolution" : 152.7032318115234
      },
      {
         "elevation" : 87.33883666992188,
         "location" : {
            "lat" : 43.12434,
            "lng" : 17.73767
         },
         "resolution" : 152.7032318115234
      },
      {
         "elevation" : 88.03240203857422,
         "location" : {
            "lat" : 43.12452,
            "lng" : 17.73767
         },
         "resolution" : 152.7032318115234
      },
      {
         "elevation" : 88.76450347900391,
         "location" : {
            "lat" : 43.12471,
            "lng" : 17.73767
         },
         "resolution" : 152.7032318115234
      },
      {
         "elevation" : 89.18769836425781,
         "location" : {
            "lat" : 43.1249,
            "lng" : 17.73767
         },
         "resolution" : 152.7032318115234
      },
      {
         "elevation" : 89.44984436035156,
         "location" : {
            "lat" : 43.12508,
            "lng" : 17.73767
         },
         "resolution" : 152.7032318115234
      },
      {
         "elevation" : 89.72654724121094,
         "location" : {
            "lat" : 43.12527,
            "lng" : 17.73767
         },
         "resolution" : 152.7032318115234
      },
      {
         "elevation" : 89.98869323730469,
         "location" : {
            "lat" : 43.12545,
            "lng" : 17.73767
         },
         "resolution" : 152.7032318115234
      },
      {
         "elevation" : 90,
         "location" : {
            "lat" : 43.12564,
            "lng" : 17.73767
         },
         "resolution" : 152.7032318115234
      },
      {
         "elevation" : 90,
         "location" : {
            "lat" : 43.12583,
            "lng" : 17.73767
         },
         "resolution" : 152.7032318115234
      },
      {
         "elevation" : 90,
         "location" : {
            "lat" : 43.12601,
            "lng" : 17.73767
         },
         "resolution" : 152.7032318115234
      },
      {
         "elevation" : 90.08096313476562,
         "location" : {
            "lat" : 43.1262,
            "lng" : 17.73767
         },
         "resolution" : 152.7032318115234
      },
      {
         "elevation" : 90.34310150146484,
         "location" : {
            "lat" : 43.12638,
            "lng" : 17.73767
         },
         "resolution" : 152.7032318115234
      },
      {
         "elevation" : 90.61981201171875,
         "location" : {
            "lat" : 43.12657,
            "lng" : 17.73767
         },
         "resolution" : 152.7032318115234
      },
      {
         "elevation" : 90.89652252197266,
         "location" : {
            "lat" : 43.12676,
            "lng" : 17.73767
         },
         "resolution" : 152.7032318115234
      },
      {
         "elevation" : 91.27107238769531,
         "location" : {
            "lat" : 43.12694,
            "lng" : 17.73767
         },
         "resolution" : 152.7032318115234
      },
      {
         "elevation" : 91.74382781982422,
         "location" : {
            "lat" : 43.12713,
            "lng" : 17.73767
         },
         "resolution" : 152.7032318115234
      },
      {
         "elevation" : 92.21658325195312,
         "location" : {
            "lat" : 43.12732,
            "lng" : 17.73767
         },
         "resolution" : 152.7032318115234
      },
      {
         "elevation" : 92.66445159912109,
         "location" : {
            "lat" : 43.1275,
            "lng" : 17.73767
         },
         "resolution" : 152.7032318115234
      },
      {
         "elevation" : 93.5501708984375,
         "location" : {
            "lat" : 43.12769,
            "lng" : 17.73767
         },
         "resolution" : 152.7032318115234
      },
      {
         "elevation" : 94.42947387695312,
         "location" : {
            "lat" : 43.12787,
            "lng" : 17.73767
         },
         "resolution" : 152.7032318115234
      },
      {
         "elevation" : 95.35761260986328,
         "location" : {
            "lat" : 43.12806,
            "lng" : 17.73767
         },
         "resolution" : 152.7032318115234
      },
      {
         "elevation" : 96.10567474365234,
         "location" : {
            "lat" : 43.12825,
            "lng" : 17.73767
         },
         "resolution" : 152.7032318115234
      },
      {
         "elevation" : 96.27495574951172,
         "location" : {
            "lat" : 43.12843,
            "lng" : 17.73767
         },
         "resolution" : 152.7032318115234
      },
      {
         "elevation" : 96.45364379882812,
         "location" : {
            "lat" : 43.12862,
            "lng" : 17.73767
         },
         "resolution" : 152.7032318115234
      },
      {
         "elevation" : 96.6229248046875,
         "location" : {
            "lat" : 43.1288,
            "lng" : 17.73767
         },
         "resolution" : 152.7032318115234
      },
      {
         "elevation" : 96.65741729736328,
         "location" : {
            "lat" : 43.12899,
            "lng" : 17.73767
         },
         "resolution" : 152.7032318115234
      },
      {
         "elevation" : 96.56455230712891,
         "location" : {
            "lat" : 43.12917,
            "lng" : 17.73767
         },
         "resolution" : 152.7032318115234
      },
      {
         "elevation" : 96.46652984619141,
         "location" : {
            "lat" : 43.12936,
            "lng" : 17.73767
         },
         "resolution" : 152.7032318115234
      },
      {
         "elevation" : 96.36850738525391,
         "location" : {
            "lat" : 43.12955,
            "lng" : 17.73767
         },
         "resolution" : 152.7032318115234
      },
      {
         "elevation" : 96.19703674316406,
         "location" : {
            "lat" : 43.12973,
            "lng" : 17.73767
         },
         "resolution" : 152.7032318115234
      },
      {
         "elevation" : 96.00099182128906,
         "location" : {
            "lat" : 43.12992,
            "lng" : 17.73767
         },
         "resolution" : 152.7032318115234
      },
      {
         "elevation" : 95.81526184082031,
         "location" : {
            "lat" : 43.1301,
            "lng" : 17.73767
         },
         "resolution" : 152.7032318115234
      },
      {
         "elevation" : 95.60829925537109,
         "location" : {
            "lat" : 43.13029,
            "lng" : 17.73767
         },
         "resolution" : 152.7032318115234
      },
      {
         "elevation" : 95.33158874511719,
         "location" : {
            "lat" : 43.13048,
            "lng" : 17.73767
         },
         "resolution" : 152.7032318115234
      },
      {
         "elevation" : 95.06945037841797,
         "location" : {
            "lat" : 43.13066,
            "lng" : 17.73767
         },
         "resolution" : 152.7032318115234
      },
      {
         "elevation" : 94.79273986816406,
         "location" : {
            "lat" : 43.13085,
            "lng" : 17.73767
         },
         "resolution" : 152.7032318115234
      },
      {
         "elevation" : 94.95043182373047,
         "location" : {
            "lat" : 43.13103,
            "lng" : 17.73767
         },
         "resolution" : 152.7032318115234
      },
      {
         "elevation" : 95.68253326416016,
         "location" : {
            "lat" : 43.13122,
            "lng" : 17.73767
         },
         "resolution" : 152.7032318115234
      },
      {
         "elevation" : 96.41462707519531,
         "location" : {
            "lat" : 43.13141,
            "lng" : 17.73767
         },
         "resolution" : 152.7032318115234
      },
      {
         "elevation" : 97.10820007324219,
         "location" : {
            "lat" : 43.13159,
            "lng" : 17.73767
         },
         "resolution" : 152.7032318115234
      },
      {
         "elevation" : 97.14454650878906,
         "location" : {
            "lat" : 43.13178,
            "lng" : 17.73767
         },
         "resolution" : 152.7032318115234
      },
      {
         "elevation" : 96.94850158691406,
         "location" : {
            "lat" : 43.13197,
            "lng" : 17.73767
         },
         "resolution" : 152.7032318115234
      },
      {
         "elevation" : 96.76277160644531,
         "location" : {
            "lat" : 43.13215,
            "lng" : 17.73767
         },
         "resolution" : 152.7032318115234
      },
      {
         "elevation" : 96.57630920410156,
         "location" : {
            "lat" : 43.13234,
            "lng" : 17.73767
         },
         "resolution" : 152.7032318115234
      },
      {
         "elevation" : 96.49989318847656,
         "location" : {
            "lat" : 43.13252,
            "lng" : 17.73767
         },
         "resolution" : 152.7032318115234
      },
      {
         "elevation" : 96.41923522949219,
         "location" : {
            "lat" : 43.13271,
            "lng" : 17.73767
         },
         "resolution" : 152.7032318115234
      },
      {
         "elevation" : 96.33856964111328,
         "location" : {
            "lat" : 43.1329,
            "lng" : 17.73767
         },
         "resolution" : 152.7032318115234
      },
      {
         "elevation" : 96.29782104492188,
         "location" : {
            "lat" : 43.13308,
            "lng" : 17.73767
         },
         "resolution" : 152.7032318115234
      },
      {
         "elevation" : 96.315185546875,
         "location" : {
            "lat" : 43.13327,
            "lng" : 17.73767
         },
         "resolution" : 152.7032318115234
      },
      {
         "elevation" : 96.33163452148438,
         "location" : {
            "lat" : 43.13345,
            "lng" : 17.73767
         },
         "resolution" : 152.7032318115234
      },
      {
         "elevation" : 96.34899139404297,
         "location" : {
            "lat" : 43.13364,
            "lng" : 17.73767
         },
         "resolution" : 152.7032318115234
      },
      {
         "elevation" : 96.61555480957031,
         "location" : {
            "lat" : 43.13383,
            "lng" : 17.73767
         },
         "resolution" : 152.7032318115234
      },
      {
         "elevation" : 96.97055816650391,
         "location" : {
            "lat" : 43.13401,
            "lng" : 17.73767
         },
         "resolution" : 152.7032318115234
      },
      {
         "elevation" : 97.34529113769531,
         "location" : {
            "lat" : 43.1342,
            "lng" : 17.73767
         },
         "resolution" : 152.7032318115234
      },
      {
         "elevation" : 97.70030212402344,
         "location" : {
            "lat" : 43.13438,
            "lng" : 17.73767
         },
         "resolution" : 152.7032318115234
      },
      {
         "elevation" : 98.24980926513672,
         "location" : {
            "lat" : 43.13457,
            "lng" : 17.73767
         },
         "resolution" : 152.7032318115234
      },
      {
         "elevation" : 98.77409362792969,
         "location" : {
            "lat" : 43.13475,
            "lng" : 17.73767
         },
         "resolution" : 152.7032318115234
      },
      {
         "elevation" : 99.32750701904297,
         "location" : {
            "lat" : 43.13494,
            "lng" : 17.73767
         },
         "resolution" : 152.7032318115234
      },
      {
         "elevation" : 99.88092803955078,
         "location" : {
            "lat" : 43.13513,
            "lng" : 17.73767
         },
         "resolution" : 152.7032318115234
      },
      {
         "elevation" : 100.4052124023438,
         "location" : {
            "lat" : 43.13531,
            "lng" : 17.73767
         },
         "resolution" : 152.7032318115234
      },
      {
         "elevation" : 100.958625793457,
         "location" : {
            "lat" : 43.1355,
            "lng" : 17.73767
         },
         "resolution" : 152.7032318115234
      },
      {
         "elevation" : 101.4829177856445,
         "location" : {
            "lat" : 43.13568,
            "lng" : 17.73767
         },
         "resolution" : 152.7032318115234
      },
      {
         "elevation" : 101.8143463134766,
         "location" : {
            "lat" : 43.13587,
            "lng" : 17.73767
         },
         "resolution" : 152.7032318115234
      },
      {
         "elevation" : 101.9930267333984,
         "location" : {
            "lat" : 43.13606,
            "lng" : 17.73767
         },
         "resolution" : 152.7032318115234
      },
      {
         "elevation" : 102.1717147827148,
         "location" : {
            "lat" : 43.13625,
            "lng" : 17.73767
         },
         "resolution" : 152.7032318115234
      },
      {
         "elevation" : 102.3409957885742,
         "location" : {
            "lat" : 43.13643,
            "lng" : 17.73767
         },
         "resolution" : 152.7032318115234
      },
      {
         "elevation" : 102.7758636474609,
         "location" : {
            "lat" : 43.13662,
            "lng" : 17.73767
         },
         "resolution" : 152.7032318115234
      },
      {
         "elevation" : 103.2072906494141,
         "location" : {
            "lat" : 43.1368,
            "lng" : 17.73767
         },
         "resolution" : 152.7032318115234
      },
      {
         "elevation" : 103.6626815795898,
         "location" : {
            "lat" : 43.13699,
            "lng" : 17.73767
         },
         "resolution" : 152.7032318115234
      },
      {
         "elevation" : 104.1346206665039,
         "location" : {
            "lat" : 43.13717,
            "lng" : 17.73767
         },
         "resolution" : 152.7032318115234
      },
      {
         "elevation" : 104.7860565185547,
         "location" : {
            "lat" : 43.13736,
            "lng" : 17.73767
         },
         "resolution" : 152.7032318115234
      },
      {
         "elevation" : 105.4374923706055,
         "location" : {
            "lat" : 43.13755,
            "lng" : 17.73767
         },
         "resolution" : 152.7032318115234
      },
      {
         "elevation" : 106.0546417236328,
         "location" : {
            "lat" : 43.13773,
            "lng" : 17.73767
         },
         "resolution" : 152.7032318115234
      },
      {
         "elevation" : 106.7060852050781,
         "location" : {
            "lat" : 43.13792,
            "lng" : 17.73767
         },
         "resolution" : 152.7032318115234
      },
      {
         "elevation" : 107.3232345581055,
         "location" : {
            "lat" : 43.1381,
            "lng" : 17.73767
         },
         "resolution" : 152.7032318115234
      },
      {
         "elevation" : 107.9746704101562,
         "location" : {
            "lat" : 43.13829,
            "lng" : 17.73767
         },
         "resolution" : 152.7032318115234
      },
      {
         "elevation" : 108.6261138916016,
         "location" : {
            "lat" : 43.13848,
            "lng" : 17.73767
         },
         "resolution" : 152.7032318115234
      },
      {
         "elevation" : 109.0018615722656,
         "location" : {
            "lat" : 43.13866,
            "lng" : 17.73767
         },
         "resolution" : 152.7032318115234
      },
      {
         "elevation" : 109.3592300415039,
         "location" : {
            "lat" : 43.13885,
            "lng" : 17.73767
         },
         "resolution" : 152.7032318115234
      },
      {
         "elevation" : 109.6977920532227,
         "location" : {
            "lat" : 43.13903,
            "lng" : 17.73767
         },
         "resolution" : 152.7032318115234
      },
      {
         "elevation" : 110.0427093505859,
         "location" : {
            "lat" : 43.13922,
            "lng" : 17.73767
         },
         "resolution" : 152.7032318115234
      },
      {
         "elevation" : 110.3194198608398,
         "location" : {
            "lat" : 43.13941,
            "lng" : 17.73767
         },
         "resolution" : 152.7032318115234
      },
      {
         "elevation" : 110.5815582275391,
         "location" : {
            "lat" : 43.13959,
            "lng" : 17.73767
         },
         "resolution" : 152.7032318115234
      },
      {
         "elevation" : 110.858268737793,
         "location" : {
            "lat" : 43.13978,
            "lng" : 17.73767
         },
         "resolution" : 152.7032318115234
      },
      {
         "elevation" : 110.7778625488281,
         "location" : {
            "lat" : 43.13997,
            "lng" : 17.73767
         },
         "resolution" : 152.7032318115234
      },
      {
         "elevation" : 110.346435546875,
         "location" : {
            "lat" : 43.14015,
            "lng" : 17.73767
         },
         "resolution" : 152.7032318115234
      },
      {
         "elevation" : 109.8910446166992,
         "location" : {
            "lat" : 43.14034,
            "lng" : 17.73767
         },
         "resolution" : 152.7032318115234
      },
      {
         "elevation" : 109.4596252441406,
         "location" : {
            "lat" : 43.14052,
            "lng" : 17.73767
         },
         "resolution" : 152.7032318115234
      },
      {
         "elevation" : 109.2789077758789,
         "location" : {
            "lat" : 43.14071,
            "lng" : 17.73767
         },
         "resolution" : 152.7032318115234
      },
      {
         "elevation" : 109.1808853149414,
         "location" : {
            "lat" : 43.1409,
            "lng" : 17.73767
         },
         "resolution" : 152.7032318115234
      },
      {
         "elevation" : 109.088020324707,
         "location" : {
            "lat" : 43.14108,
            "lng" : 17.73767
         },
         "resolution" : 152.7032318115234
      },
      {
         "elevation" : 108.9899978637695,
         "location" : {
            "lat" : 43.14127,
            "lng" : 17.73767
         },
         "resolution" : 152.7032318115234
      },
      {
         "elevation" : 108.8971328735352,
         "location" : {
            "lat" : 43.14145,
            "lng" : 17.73767
         },
         "resolution" : 152.7032318115234
      },
      {
         "elevation" : 108.7991104125977,
         "location" : {
            "lat" : 43.14164,
            "lng" : 17.73767
         },
         "resolution" : 152.7032318115234
      },
      {
         "elevation" : 108.7062454223633,
         "location" : {
            "lat" : 43.14182,
            "lng" : 17.73767
         },
         "resolution" : 152.7032318115234
      },
      {
         "elevation" : 108.3654556274414,
         "location" : {
            "lat" : 43.14201,
            "lng" : 17.73767
         },
         "resolution" : 152.7032318115234
      },
      {
         "elevation" : 107.6333618164062,
         "location" : {
            "lat" : 43.1422,
            "lng" : 17.73767
         },
         "resolution" : 152.7032318115234
      },
      {
         "elevation" : 106.9397888183594,
         "location" : {
            "lat" : 43.14238,
            "lng" : 17.73767
         },
         "resolution" : 152.7032318115234
      },
      {
         "elevation" : 106.2076873779297,
         "location" : {
            "lat" : 43.14257,
            "lng" : 17.73767
         },
         "resolution" : 152.7032318115234
      },
      {
         "elevation" : 105.8163528442383,
         "location" : {
            "lat" : 43.14275,
            "lng" : 17.73767
         },
         "resolution" : 152.7032318115234
      },
      {
         "elevation" : 105.5396499633789,
         "location" : {
            "lat" : 43.14294,
            "lng" : 17.73767
         },
         "resolution" : 152.7032318115234
      },
      {
         "elevation" : 105.262939453125,
         "location" : {
            "lat" : 43.14313,
            "lng" : 17.73767
         },
         "resolution" : 152.7032318115234
      },
      {
         "elevation" : 105.0007934570312,
         "location" : {
            "lat" : 43.14331,
            "lng" : 17.73767
         },
         "resolution" : 152.7032318115234
      },
      {
         "elevation" : 105.3563385009766,
         "location" : {
            "lat" : 43.1435,
            "lng" : 17.73767
         },
         "resolution" : 152.7032318115234
      },
      {
         "elevation" : 105.6949005126953,
         "location" : {
            "lat" : 43.14368,
            "lng" : 17.73767
         },
         "resolution" : 152.7032318115234
      },
      {
         "elevation" : 106.0522689819336,
         "location" : {
            "lat" : 43.14387,
            "lng" : 17.73767
         },
         "resolution" : 152.7032318115234
      },
      {
         "elevation" : 106.4477844238281,
         "location" : {
            "lat" : 43.14406,
            "lng" : 17.73767
         },
         "resolution" : 152.7032318115234
      },
      {
         "elevation" : 106.8956527709961,
         "location" : {
            "lat" : 43.14424,
            "lng" : 17.73767
         },
         "resolution" : 152.7032318115234
      },
      {
         "elevation" : 107.368408203125,
         "location" : {
            "lat" : 43.14443,
            "lng" : 17.73767
         },
         "resolution" : 152.7032318115234
      },
      {
         "elevation" : 107.8411636352539,
         "location" : {
            "lat" : 43.14462,
            "lng" : 17.73767
         },
         "resolution" : 152.7032318115234
      },
      {
         "elevation" : 108.2784194946289,
         "location" : {
            "lat" : 43.1448,
            "lng" : 17.73767
         },
         "resolution" : 152.7032318115234
      },
      {
         "elevation" : 108.7338104248047,
         "location" : {
            "lat" : 43.14499,
            "lng" : 17.73767
         },
         "resolution" : 152.7032318115234
      },
      {
         "elevation" : 109.1652374267578,
         "location" : {
            "lat" : 43.14517,
            "lng" : 17.73767
         },
         "resolution" : 152.7032318115234
      },
      {
         "elevation" : 109.6206283569336,
         "location" : {
            "lat" : 43.14536,
            "lng" : 17.73767
         },
         "resolution" : 152.7032318115234
      },
      {
         "elevation" : 107.5378265380859,
         "location" : {
            "lat" : 43.14555,
            "lng" : 17.73767
         },
         "resolution" : 152.7032318115234
      },
      {
         "elevation" : 105.4242324829102,
         "location" : {
            "lat" : 43.14573,
            "lng" : 17.73767
         },
         "resolution" : 152.7032318115234
      },
      {
         "elevation" : 103.1932067871094,
         "location" : {
            "lat" : 43.14592,
            "lng" : 17.73767
         },
         "resolution" : 152.7032318115234
      },
      {
         "elevation" : 99.84909820556641,
         "location" : {
            "lat" : 43.1461,
            "lng" : 17.73767
         },
         "resolution" : 152.7032318115234
      }
   ],
   "status" : "OK"
}
