{
   "results" : [
      {
         "elevation" : 966.6064453125,
         "location" : {
            "lat" : 37.00565,
            "lng" : 31.77302
         },
         "resolution" : 152.7032318115234
      },
      {
         "elevation" : 965.1621704101562,
         "location" : {
            "lat" : 37.00591,
            "lng" : 31.77302
         },
         "resolution" : 152.7032318115234
      },
      {
         "elevation" : 965.0418701171875,
         "location" : {
            "lat" : 37.00617,
            "lng" : 31.77302
         },
         "resolution" : 152.7032318115234
      },
      {
         "elevation" : 967.1461791992188,
         "location" : {
            "lat" : 37.00643,
            "lng" : 31.77302
         },
         "resolution" : 152.7032318115234
      },
      {
         "elevation" : 969.2505493164062,
         "location" : {
            "lat" : 37.00669,
            "lng" : 31.77302
         },
         "resolution" : 152.7032318115234
      },
      {
         "elevation" : 971.3548583984375,
         "location" : {
            "lat" : 37.00695,
            "lng" : 31.77302
         },
         "resolution" : 152.7032318115234
      },
      {
         "elevation" : 973.4591674804688,
         "location" : {
            "lat" : 37.00721,
            "lng" : 31.77302
         },
         "resolution" : 152.7032318115234
      },
      {
         "elevation" : 975.6759643554688,
         "location" : {
            "lat" : 37.00747,
            "lng" : 31.77302
         },
         "resolution" : 152.7032318115234
      },
      {
         "elevation" : 979.141845703125,
         "location" : {
            "lat" : 37.00774,
            "lng" : 31.77302
         },
         "resolution" : 152.7032318115234
      },
      {
         "elevation" : 982.4793701171875,
         "location" : {
            "lat" : 37.008,
            "lng" : 31.77302
         },
         "resolution" : 152.7032318115234
      },
      {
         "elevation" : 985.481201171875,
         "location" : {
            "lat" : 37.00826,
            "lng" : 31.77302
         },
         "resolution" : 152.7032318115234
      },
      {
         "elevation" : 988.1317138671875,
         "location" : {
            "lat" : 37.00852,
            "lng" : 31.77302
         },
         "resolution" : 152.7032318115234
      },
      {
         "elevation" : 990.7822875976562,
         "location" : {
            "lat" : 37.00878,
            "lng" : 31.77302
         },
         "resolution" : 152.7032318115234
      },
      {
         "elevation" : 991.8278198242188,
         "location" : {
            "lat" : 37.00904,
            "lng" : 31.77302
         },
         "resolution" : 152.7032318115234
      },
      {
         "elevation" : 992.5851440429688,
         "location" : {
            "lat" : 37.0093,
            "lng" : 31.77302
         },
         "resolution" : 152.7032318115234
      },
      {
         "elevation" : 993.1074829101562,
         "location" : {
            "lat" : 37.00956,
            "lng" : 31.77302
         },
         "resolution" : 152.7032318115234
      },
      {
         "elevation" : 992.7142944335938,
         "location" : {
            "lat" : 37.00983,
            "lng" : 31.77302
         },
         "resolution" : 152.7032318115234
      },
      {
         "elevation" : 992.3356323242188,
         "location" : {
            "lat" : 37.01009,
            "lng" : 31.77302
         },
         "resolution" : 152.7032318115234
      },
      {
         "elevation" : 991.8719482421875,
         "location" : {
            "lat" : 37.01035,
            "lng" : 31.77302
         },
         "resolution" : 152.7032318115234
      },
      {
         "elevation" : 991.3525390625,
         "location" : {
            "lat" : 37.01061,
            "lng" : 31.77302
         },
         "resolution" : 152.7032318115234
      },
      {
         "elevation" : 990.8331909179688,
         "location" : {
            "lat" : 37.01087,
            "lng" : 31.77302
         },
         "resolution" : 152.7032318115234
      },
      {
         "elevation" : 992.7737426757812,
         "location" : {
            "lat" : 37.01113,
            "lng" : 31.77302
         },
         "resolution" : 152.7032318115234
      },
      {
         "elevation" : 994.8076782226562,
         "location" : {
            "lat" : 37.01139,
            "lng" : 31.77302
         },
         "resolution" : 152.7032318115234
      },
      {
         "elevation" : 997.4608154296875,
         "location" : {
            "lat" : 37.01165,
            "lng" : 31.77302
         },
         "resolution" : 152.7032318115234
      },
      {
         "elevation" : 1001.567016601562,
         "location" : {
            "lat" : 37.01192,
            "lng" : 31.77302
         },
         "resolution" : 152.7032318115234
      },
      {
         "elevation" : 1005.521118164062,
         "location" : {
            "lat" : 37.01218,
            "lng" : 31.77302
         },
         "resolution" : 152.7032318115234
      },
      {
         "elevation" : 1010.172424316406,
         "location" : {
            "lat" : 37.01244,
            "lng" : 31.77302
         },
         "resolution" : 152.7032318115234
      },
      {
         "elevation" : 1015.094909667969,
         "location" : {
            "lat" : 37.0127,
            "lng" : 31.77302
         },
         "resolution" : 152.7032318115234
      },
      {
         "elevation" : 1020.02294921875,
         "location" : {
            "lat" : 37.01296,
            "lng" : 31.77302
         },
         "resolution" : 152.7032318115234
      },
      {
         "elevation" : 1025.015747070312,
         "location" : {
            "lat" : 37.01322,
            "lng" : 31.77302
         },
         "resolution" : 152.7032318115234
      },
      {
         "elevation" : 1030.008666992188,
         "location" : {
            "lat" : 37.01348,
            "lng" : 31.77302
         },
         "resolution" : 152.7032318115234
      },
      {
         "elevation" : 1034.7431640625,
         "location" : {
            "lat" : 37.01374,
            "lng" : 31.77302
         },
         "resolution" : 152.7032318115234
      },
      {
         "elevation" : 1039.315551757812,
         "location" : {
            "lat" : 37.01401,
            "lng" : 31.77302
         },
         "resolution" : 152.7032318115234
      },
      {
         "elevation" : 1043.71875,
         "location" : {
            "lat" : 37.01427,
            "lng" : 31.77302
         },
         "resolution" : 152.7032318115234
      },
      {
         "elevation" : 1047.606567382812,
         "location" : {
            "lat" : 37.01453,
            "lng" : 31.77302
         },
         "resolution" : 152.7032318115234
      },
      {
         "elevation" : 1051.39306640625,
         "location" : {
            "lat" : 37.01479,
            "lng" : 31.77302
         },
         "resolution" : 152.7032318115234
      },
      {
         "elevation" : 1055.160766601562,
         "location" : {
            "lat" : 37.01505,
            "lng" : 31.77302
         },
         "resolution" : 152.7032318115234
      },
      {
         "elevation" : 1058.849975585938,
         "location" : {
            "lat" : 37.01531,
            "lng" : 31.77302
         },
         "resolution" : 152.7032318115234
      },
      {
         "elevation" : 1062.68115234375,
         "location" : {
            "lat" : 37.01558,
            "lng" : 31.77302
         },
         "resolution" : 152.7032318115234
      },
      {
         "elevation" : 1066.662841796875,
         "location" : {
            "lat" : 37.01583,
            "lng" : 31.77302
         },
         "resolution" : 152.7032318115234
      },
      {
         "elevation" : 1071.308349609375,
         "location" : {
            "lat" : 37.0161,
            "lng" : 31.77302
         },
         "resolution" : 152.7032318115234
      },
      {
         "elevation" : 1075.781860351562,
         "location" : {
            "lat" : 37.01636,
            "lng" : 31.77302
         },
         "resolution" : 152.7032318115234
      },
      {
         "elevation" : 1078.814575195312,
         "location" : {
            "lat" : 37.01662,
            "lng" : 31.77302
         },
         "resolution" : 152.7032318115234
      },
      {
         "elevation" : 1081.7734375,
         "location" : {
            "lat" : 37.01688,
            "lng" : 31.77302
         },
         "resolution" : 152.7032318115234
      },
      {
         "elevation" : 1084.262329101562,
         "location" : {
            "lat" : 37.01714,
            "lng" : 31.77302
         },
         "resolution" : 152.7032318115234
      },
      {
         "elevation" : 1085.70654296875,
         "location" : {
            "lat" : 37.0174,
            "lng" : 31.77302
         },
         "resolution" : 152.7032318115234
      },
      {
         "elevation" : 1087.206420898438,
         "location" : {
            "lat" : 37.01767,
            "lng" : 31.77302
         },
         "resolution" : 152.7032318115234
      },
      {
         "elevation" : 1088.064819335938,
         "location" : {
            "lat" : 37.01793,
            "lng" : 31.77302
         },
         "resolution" : 152.7032318115234
      },
      {
         "elevation" : 1088.681396484375,
         "location" : {
            "lat" : 37.01819,
            "lng" : 31.77302
         },
         "resolution" : 152.7032318115234
      },
      {
         "elevation" : 1089.259643554688,
         "location" : {
            "lat" : 37.01845,
            "lng" : 31.77302
         },
         "resolution" : 152.7032318115234
      },
      {
         "elevation" : 1089.30322265625,
         "location" : {
            "lat" : 37.01871,
            "lng" : 31.77302
         },
         "resolution" : 152.7032318115234
      },
      {
         "elevation" : 1089.3466796875,
         "location" : {
            "lat" : 37.01897,
            "lng" : 31.77302
         },
         "resolution" : 152.7032318115234
      },
      {
         "elevation" : 1090.841552734375,
         "location" : {
            "lat" : 37.01923,
            "lng" : 31.77302
         },
         "resolution" : 152.7032318115234
      },
      {
         "elevation" : 1094.29296875,
         "location" : {
            "lat" : 37.01949,
            "lng" : 31.77302
         },
         "resolution" : 152.7032318115234
      },
      {
         "elevation" : 1097.877075195312,
         "location" : {
            "lat" : 37.01976,
            "lng" : 31.77302
         },
         "resolution" : 152.7032318115234
      },
      {
         "elevation" : 1102.69140625,
         "location" : {
            "lat" : 37.02002,
            "lng" : 31.77302
         },
         "resolution" : 152.7032318115234
      },
      {
         "elevation" : 1107.798095703125,
         "location" : {
            "lat" : 37.02028,
            "lng" : 31.77302
         },
         "resolution" : 152.7032318115234
      },
      {
         "elevation" : 1113.073608398438,
         "location" : {
            "lat" : 37.02054,
            "lng" : 31.77302
         },
         "resolution" : 152.7032318115234
      },
      {
         "elevation" : 1119.105102539062,
         "location" : {
            "lat" : 37.0208,
            "lng" : 31.77302
         },
         "resolution" : 152.7032318115234
      },
      {
         "elevation" : 1125.13671875,
         "location" : {
            "lat" : 37.02106,
            "lng" : 31.77302
         },
         "resolution" : 152.7032318115234
      },
      {
         "elevation" : 1130.772705078125,
         "location" : {
            "lat" : 37.02132,
            "lng" : 31.77302
         },
         "resolution" : 152.7032318115234
      },
      {
         "elevation" : 1136.073852539062,
         "location" : {
            "lat" : 37.02158,
            "lng" : 31.77302
         },
         "resolution" : 152.7032318115234
      },
      {
         "elevation" : 1141.578857421875,
         "location" : {
            "lat" : 37.02185,
            "lng" : 31.77302
         },
         "resolution" : 152.7032318115234
      },
      {
         "elevation" : 1144.218017578125,
         "location" : {
            "lat" : 37.02211,
            "lng" : 31.77302
         },
         "resolution" : 152.7032318115234
      },
      {
         "elevation" : 1146.684326171875,
         "location" : {
            "lat" : 37.02237,
            "lng" : 31.77302
         },
         "resolution" : 152.7032318115234
      },
      {
         "elevation" : 1148.050903320312,
         "location" : {
            "lat" : 37.02263,
            "lng" : 31.77302
         },
         "resolution" : 152.7032318115234
      },
      {
         "elevation" : 1146.828002929688,
         "location" : {
            "lat" : 37.02289,
            "lng" : 31.77302
         },
         "resolution" : 152.7032318115234
      },
      {
         "elevation" : 1145.605102539062,
         "location" : {
            "lat" : 37.02315,
            "lng" : 31.77302
         },
         "resolution" : 152.7032318115234
      },
      {
         "elevation" : 1141.37841796875,
         "location" : {
            "lat" : 37.02341,
            "lng" : 31.77302
         },
         "resolution" : 152.7032318115234
      },
      {
         "elevation" : 1135.584838867188,
         "location" : {
            "lat" : 37.02367,
            "lng" : 31.77302
         },
         "resolution" : 152.7032318115234
      },
      {
         "elevation" : 1129.5966796875,
         "location" : {
            "lat" : 37.02394,
            "lng" : 31.77302
         },
         "resolution" : 152.7032318115234
      },
      {
         "elevation" : 1124.322509765625,
         "location" : {
            "lat" : 37.0242,
            "lng" : 31.77302
         },
         "resolution" : 152.7032318115234
      },
      {
         "elevation" : 1119.048217773438,
         "location" : {
            "lat" : 37.02446,
            "lng" : 31.77302
         },
         "resolution" : 152.7032318115234
      },
      {
         "elevation" : 1113.263671875,
         "location" : {
            "lat" : 37.02472,
            "lng" : 31.77302
         },
         "resolution" : 152.7032318115234
      },
      {
         "elevation" : 1106.756225585938,
         "location" : {
            "lat" : 37.02498,
            "lng" : 31.77302
         },
         "resolution" : 152.7032318115234
      },
      {
         "elevation" : 1100.248779296875,
         "location" : {
            "lat" : 37.02524,
            "lng" : 31.77302
         },
         "resolution" : 152.7032318115234
      },
      {
         "elevation" : 1091.876342773438,
         "location" : {
            "lat" : 37.02551,
            "lng" : 31.77302
         },
         "resolution" : 152.7032318115234
      },
      {
         "elevation" : 1083.705200195312,
         "location" : {
            "lat" : 37.02576,
            "lng" : 31.77302
         },
         "resolution" : 152.7032318115234
      },
      {
         "elevation" : 1074.803955078125,
         "location" : {
            "lat" : 37.02603,
            "lng" : 31.77302
         },
         "resolution" : 152.7032318115234
      },
      {
         "elevation" : 1065.85693359375,
         "location" : {
            "lat" : 37.02629,
            "lng" : 31.77302
         },
         "resolution" : 152.7032318115234
      },
      {
         "elevation" : 1056.910034179688,
         "location" : {
            "lat" : 37.02655,
            "lng" : 31.77302
         },
         "resolution" : 152.7032318115234
      },
      {
         "elevation" : 1046.559936523438,
         "location" : {
            "lat" : 37.02681,
            "lng" : 31.77302
         },
         "resolution" : 152.7032318115234
      },
      {
         "elevation" : 1034.96240234375,
         "location" : {
            "lat" : 37.02707,
            "lng" : 31.77302
         },
         "resolution" : 152.7032318115234
      },
      {
         "elevation" : 1023.364929199219,
         "location" : {
            "lat" : 37.02733,
            "lng" : 31.77302
         },
         "resolution" : 152.7032318115234
      },
      {
         "elevation" : 1013.492370605469,
         "location" : {
            "lat" : 37.0276,
            "lng" : 31.77302
         },
         "resolution" : 152.7032318115234
      },
      {
         "elevation" : 1004.593139648438,
         "location" : {
            "lat" : 37.02785,
            "lng" : 31.77302
         },
         "resolution" : 152.7032318115234
      },
      {
         "elevation" : 995.6315307617188,
         "location" : {
            "lat" : 37.02812,
            "lng" : 31.77302
         },
         "resolution" : 152.7032318115234
      },
      {
         "elevation" : 988.648193359375,
         "location" : {
            "lat" : 37.02838,
            "lng" : 31.77302
         },
         "resolution" : 152.7032318115234
      },
      {
         "elevation" : 981.6648559570312,
         "location" : {
            "lat" : 37.02864,
            "lng" : 31.77302
         },
         "resolution" : 152.7032318115234
      },
      {
         "elevation" : 976.499267578125,
         "location" : {
            "lat" : 37.0289,
            "lng" : 31.77302
         },
         "resolution" : 152.7032318115234
      },
      {
         "elevation" : 972.3341064453125,
         "location" : {
            "lat" : 37.02916,
            "lng" : 31.77302
         },
         "resolution" : 152.7032318115234
      },
      {
         "elevation" : 968.1815795898438,
         "location" : {
            "lat" : 37.02942,
            "lng" : 31.77302
         },
         "resolution" : 152.7032318115234
      },
      {
         "elevation" : 967.1029052734375,
         "location" : {
            "lat" : 37.02969,
            "lng" : 31.77302
         },
         "resolution" : 152.7032318115234
      },
      {
         "elevation" : 966.064208984375,
         "location" : {
            "lat" : 37.02995,
            "lng" : 31.77302
         },
         "resolution" : 152.7032318115234
      },
      {
         "elevation" : 965.9095458984375,
         "location" : {
            "lat" : 37.03021,
            "lng" : 31.77302
         },
         "resolution" : 152.7032318115234
      },
      {
         "elevation" : 967.0723876953125,
         "location" : {
            "lat" : 37.03047,
            "lng" : 31.77302
         },
         "resolution" : 152.7032318115234
      },
      {
         "elevation" : 968.2352294921875,
         "location" : {
            "lat" : 37.03073,
            "lng" : 31.77302
         },
         "resolution" : 152.7032318115234
      },
      {
         "elevation" : 969.2501220703125,
         "location" : {
            "lat" : 37.03099,
            "lng" : 31.77302
         },
         "resolution" : 152.7032318115234
      },
      {
         "elevation" : 970.218505859375,
         "location" : {
            "lat" : 37.03125,
            "lng" : 31.77302
         },
         "resolution" : 152.7032318115234
      },
      {
         "elevation" : 971.2490234375,
         "location" : {
            "lat" : 37.03151,
            "lng" : 31.77302
         },
         "resolution" : 152.7032318115234
      }
   ],
   "status" : "OK"
}
