{
   "results" : [
      {
         "elevation" : 1023.633361816406,
         "location" : {
            "lat" : 40.16512,
            "lng" : 32.94207
         },
         "resolution" : 152.7032318115234
      },
      {
         "elevation" : 1023.086242675781,
         "location" : {
            "lat" : 40.16519,
            "lng" : 32.94207
         },
         "resolution" : 152.7032318115234
      },
      {
         "elevation" : 1022.539123535156,
         "location" : {
            "lat" : 40.16526,
            "lng" : 32.94207
         },
         "resolution" : 152.7032318115234
      },
      {
         "elevation" : 1021.992553710938,
         "location" : {
            "lat" : 40.16533,
            "lng" : 32.94207
         },
         "resolution" : 152.7032318115234
      },
      {
         "elevation" : 1021.410034179688,
         "location" : {
            "lat" : 40.16541,
            "lng" : 32.94207
         },
         "resolution" : 152.7032318115234
      },
      {
         "elevation" : 1020.97314453125,
         "location" : {
            "lat" : 40.16547,
            "lng" : 32.94207
         },
         "resolution" : 152.7032318115234
      },
      {
         "elevation" : 1020.390563964844,
         "location" : {
            "lat" : 40.16555,
            "lng" : 32.94207
         },
         "resolution" : 152.7032318115234
      },
      {
         "elevation" : 1019.880859375,
         "location" : {
            "lat" : 40.16562,
            "lng" : 32.94207
         },
         "resolution" : 152.7032318115234
      },
      {
         "elevation" : 1019.371154785156,
         "location" : {
            "lat" : 40.16569,
            "lng" : 32.94207
         },
         "resolution" : 152.7032318115234
      },
      {
         "elevation" : 1018.861389160156,
         "location" : {
            "lat" : 40.16576,
            "lng" : 32.94207
         },
         "resolution" : 152.7032318115234
      },
      {
         "elevation" : 1018.278869628906,
         "location" : {
            "lat" : 40.16584,
            "lng" : 32.94207
         },
         "resolution" : 152.7032318115234
      },
      {
         "elevation" : 1017.769165039062,
         "location" : {
            "lat" : 40.16591,
            "lng" : 32.94207
         },
         "resolution" : 152.7032318115234
      },
      {
         "elevation" : 1017.259399414062,
         "location" : {
            "lat" : 40.16598,
            "lng" : 32.94207
         },
         "resolution" : 152.7032318115234
      },
      {
         "elevation" : 1016.881530761719,
         "location" : {
            "lat" : 40.16605,
            "lng" : 32.94207
         },
         "resolution" : 152.7032318115234
      },
      {
         "elevation" : 1016.605773925781,
         "location" : {
            "lat" : 40.16613,
            "lng" : 32.94207
         },
         "resolution" : 152.7032318115234
      },
      {
         "elevation" : 1016.398986816406,
         "location" : {
            "lat" : 40.16619,
            "lng" : 32.94207
         },
         "resolution" : 152.7032318115234
      },
      {
         "elevation" : 1016.123229980469,
         "location" : {
            "lat" : 40.16627,
            "lng" : 32.94207
         },
         "resolution" : 152.7032318115234
      },
      {
         "elevation" : 1015.881958007812,
         "location" : {
            "lat" : 40.16634,
            "lng" : 32.94207
         },
         "resolution" : 152.7032318115234
      },
      {
         "elevation" : 1015.640686035156,
         "location" : {
            "lat" : 40.16641,
            "lng" : 32.94207
         },
         "resolution" : 152.7032318115234
      },
      {
         "elevation" : 1015.3994140625,
         "location" : {
            "lat" : 40.16648,
            "lng" : 32.94207
         },
         "resolution" : 152.7032318115234
      },
      {
         "elevation" : 1015.123718261719,
         "location" : {
            "lat" : 40.16656,
            "lng" : 32.94207
         },
         "resolution" : 152.7032318115234
      },
      {
         "elevation" : 1014.882446289062,
         "location" : {
            "lat" : 40.16663,
            "lng" : 32.94207
         },
         "resolution" : 152.7032318115234
      },
      {
         "elevation" : 1014.641174316406,
         "location" : {
            "lat" : 40.1667,
            "lng" : 32.94207
         },
         "resolution" : 152.7032318115234
      },
      {
         "elevation" : 1014.830627441406,
         "location" : {
            "lat" : 40.16677,
            "lng" : 32.94207
         },
         "resolution" : 152.7032318115234
      },
      {
         "elevation" : 1015.063659667969,
         "location" : {
            "lat" : 40.16685,
            "lng" : 32.94207
         },
         "resolution" : 152.7032318115234
      },
      {
         "elevation" : 1015.267517089844,
         "location" : {
            "lat" : 40.16692,
            "lng" : 32.94207
         },
         "resolution" : 152.7032318115234
      },
      {
         "elevation" : 1015.471435546875,
         "location" : {
            "lat" : 40.16699,
            "lng" : 32.94207
         },
         "resolution" : 152.7032318115234
      },
      {
         "elevation" : 1015.67529296875,
         "location" : {
            "lat" : 40.16706,
            "lng" : 32.94207
         },
         "resolution" : 152.7032318115234
      },
      {
         "elevation" : 1015.879211425781,
         "location" : {
            "lat" : 40.16713,
            "lng" : 32.94207
         },
         "resolution" : 152.7032318115234
      },
      {
         "elevation" : 1016.112243652344,
         "location" : {
            "lat" : 40.16721,
            "lng" : 32.94207
         },
         "resolution" : 152.7032318115234
      },
      {
         "elevation" : 1016.316101074219,
         "location" : {
            "lat" : 40.16728,
            "lng" : 32.94207
         },
         "resolution" : 152.7032318115234
      },
      {
         "elevation" : 1016.52001953125,
         "location" : {
            "lat" : 40.16735,
            "lng" : 32.94207
         },
         "resolution" : 152.7032318115234
      },
      {
         "elevation" : 1016.752563476562,
         "location" : {
            "lat" : 40.16742,
            "lng" : 32.94207
         },
         "resolution" : 152.7032318115234
      },
      {
         "elevation" : 1017.059387207031,
         "location" : {
            "lat" : 40.1675,
            "lng" : 32.94207
         },
         "resolution" : 152.7032318115234
      },
      {
         "elevation" : 1017.327819824219,
         "location" : {
            "lat" : 40.16757,
            "lng" : 32.94207
         },
         "resolution" : 152.7032318115234
      },
      {
         "elevation" : 1017.596252441406,
         "location" : {
            "lat" : 40.16764,
            "lng" : 32.94207
         },
         "resolution" : 152.7032318115234
      },
      {
         "elevation" : 1017.86474609375,
         "location" : {
            "lat" : 40.16771,
            "lng" : 32.94207
         },
         "resolution" : 152.7032318115234
      },
      {
         "elevation" : 1018.133178710938,
         "location" : {
            "lat" : 40.16778,
            "lng" : 32.94207
         },
         "resolution" : 152.7032318115234
      },
      {
         "elevation" : 1018.401611328125,
         "location" : {
            "lat" : 40.16785,
            "lng" : 32.94207
         },
         "resolution" : 152.7032318115234
      },
      {
         "elevation" : 1018.708435058594,
         "location" : {
            "lat" : 40.16793,
            "lng" : 32.94207
         },
         "resolution" : 152.7032318115234
      },
      {
         "elevation" : 1018.976928710938,
         "location" : {
            "lat" : 40.168,
            "lng" : 32.94207
         },
         "resolution" : 152.7032318115234
      },
      {
         "elevation" : 1019.245361328125,
         "location" : {
            "lat" : 40.16807,
            "lng" : 32.94207
         },
         "resolution" : 152.7032318115234
      },
      {
         "elevation" : 1019.138427734375,
         "location" : {
            "lat" : 40.16814,
            "lng" : 32.94207
         },
         "resolution" : 152.7032318115234
      },
      {
         "elevation" : 1018.979187011719,
         "location" : {
            "lat" : 40.16822,
            "lng" : 32.94207
         },
         "resolution" : 152.7032318115234
      },
      {
         "elevation" : 1018.839904785156,
         "location" : {
            "lat" : 40.16829,
            "lng" : 32.94207
         },
         "resolution" : 152.7032318115234
      },
      {
         "elevation" : 1018.700561523438,
         "location" : {
            "lat" : 40.16836,
            "lng" : 32.94207
         },
         "resolution" : 152.7032318115234
      },
      {
         "elevation" : 1018.561218261719,
         "location" : {
            "lat" : 40.16843,
            "lng" : 32.94207
         },
         "resolution" : 152.7032318115234
      },
      {
         "elevation" : 1018.421936035156,
         "location" : {
            "lat" : 40.1685,
            "lng" : 32.94207
         },
         "resolution" : 152.7032318115234
      },
      {
         "elevation" : 1018.2626953125,
         "location" : {
            "lat" : 40.16858,
            "lng" : 32.94207
         },
         "resolution" : 152.7032318115234
      },
      {
         "elevation" : 1018.123352050781,
         "location" : {
            "lat" : 40.16865,
            "lng" : 32.94207
         },
         "resolution" : 152.7032318115234
      }
   ],
   "status" : "OK"
}
